{
    "appid": "16242256",
    "compilation-args": {
        "common": {},
        "options": [
            {
                "extra": {
                    "compileArgs": "--module cmd",
                    "ext": {},
                    "index": "pages/gonglue/list/list",
                    "query": "",
                    "scene": {}
                },
                "id": 0,
                "text": "更新"
            },
            {
                "extra": {
                    "compileArgs": "--module cmd",
                    "ext": {},
                    "index": "pages/zxinfo/zxinfo/zxinfo",
                    "query": "",
                    "scene": {}
                },
                "id": 1,
                "text": "咨询"
            },
            {
                "extra": {
                    "compileArgs": "--module cmd",
                    "ext": {},
                    "index": "pages/wenda/wenda/wenda",
                    "query": "",
                    "scene": {}
                },
                "id": 2,
                "text": "pages/wenda/wenda/wenda"
            },
            {
                "extra": {
                    "compileArgs": "--module cmd",
                    "ext": {},
                    "index": "pages/gonglue/guide/guide",
                    "query": "",
                    "scene": {}
                },
                "id": 3,
                "text": "pages/gonglue/guide/guide"
            },
            {
                "extra": {
                    "compileArgs": "--module cmd",
                    "ext": {},
                    "index": "pages/gonglue/list/list",
                    "query": "",
                    "scene": {}
                },
                "id": 4,
                "text": "pages/gonglue/list/list"
            },
            {
                "extra": {
                    "compileArgs": "--module cmd",
                    "ext": {},
                    "index": "pages/home/index/index",
                    "query": "",
                    "scene": {}
                },
                "id": 5,
                "text": "pages/home/index/index"
            },
            {
                "extra": {
                    "compileArgs": "--module cmd",
                    "ext": {},
                    "index": "pages/caseinfo/details/details",
                    "query": "cs=sz&id=1633793",
                    "scene": {}
                },
                "id": 6,
                "text": "pages/caseinfo/details/details"
            },
            {
                "extra": {
                    "compileArgs": "--module cmd",
                    "ext": {},
                    "index": "pages/caseinfo/details/details",
                    "query": "cs=sz&id=1924",
                    "scene": {}
                },
                "id": 7,
                "text": "pages/caseinfo/details/details"
            },
            {
                "extra": {
                    "compileArgs": "--module cmd",
                    "ext": {},
                    "index": "pages/company/comment/comment",
                    "query": "cs=sz&id=690037",
                    "scene": {}
                },
                "id": 8,
                "text": "业主评价"
            },
            {
                "extra": {
                    "compileArgs": "--module cmd",
                    "ext": {},
                    "index": "pages/company/xgt/xgt",
                    "query": "cs=sz&id=91587",
                    "scene": {}
                },
                "id": 9,
                "text": "案例详情"
            },
            {
                "extra": {
                    "compileArgs": "--module cmd",
                    "ext": {},
                    "index": "pages/company/details/details",
                    "query": "cs=sz&id=3712",
                    "scene": {}
                },
                "id": 10,
                "text": "公司详情"
            },
            {
                "extra": {
                    "compileArgs": "--module cmd",
                    "ext": {},
                    "index": "pages/tu/hometu/hometu",
                    "query": "",
                    "scene": {}
                },
                "id": 11,
                "text": "pages/tu/hometu/hometu"
            },
            {
                "extra": {
                    "compileArgs": "--module cmd",
                    "ext": {},
                    "index": "pages/company/xgtdetail/xgtdetail",
                    "query": "",
                    "scene": {}
                },
                "id": 12,
                "text": "pages/company/xgtdetail/xgtdetail"
            },
            {
                "extra": {
                    "compileArgs": "--module cmd",
                    "ext": {},
                    "index": "pages/tu/thematic/thematic",
                    "query": "",
                    "scene": {}
                },
                "id": 13,
                "text": "pages/tu/thematic/thematic"
            },
            {
                "extra": {
                    "compileArgs": "--module cmd",
                    "ext": {},
                    "index": "pages/company/list/list",
                    "query": "",
                    "scene": {}
                },
                "id": 14,
                "text": "pages/company/list/list"
            },
            {
                "extra": {
                    "compileArgs": "--module cmd",
                    "ext": {},
                    "index": "pages/gonglue/zhuangxiusj/zhuangxiusj",
                    "query": "",
                    "scene": {}
                },
                "id": 15,
                "text": "pages/gonglue/zhuangxiusj/zhuangxiusj"
            },
            {
                "extra": {
                    "compileArgs": "--module cmd",
                    "ext": {},
                    "index": "pages/home/index/index",
                    "query": "",
                    "scene": {
                        "channel_id": "1160000000000000",
                        "first": "分享",
                        "second": "分享"
                    }
                },
                "id": 16,
                "text": "pages/home/index/index"
            },
            {
                "extra": {
                    "compileArgs": "--module cmd",
                    "ext": {},
                    "index": "pages/gonglue/detail/detail",
                    "query": "",
                    "scene": {}
                },
                "id": 17,
                "text": "pages/gonglue/detail/detail"
            },
            {
                "extra": {
                    "compileArgs": "--module cmd",
                    "ext": {},
                    "index": "pages/design/detail/detail",
                    "query": "",
                    "scene": {}
                },
                "id": 18,
                "text": "pages/design/detail/detail"
            }
        ],
        "selected": -1
    },
    "developType": "normal",
    "host": "baiduboxapp",
    "minSwanVersion": "3.0.20",
    "preview": {
        "packageId": 787738
    },
    "projectname": "qz_xbaidu",
    "publish": {
        "hideTips": true,
        "tips": [],
        "version": "1.3.33"
    },
    "setting": {
        "urlCheck": true
    },
    "swan": {
        "baiduboxapp": {
            "swanJsVersion": "3.220.12",
            "extensionJsVersion": "1.18.3"
        }
    }
}